krml/__init__.py
krml/__main__.py
krml/py.typed
krml-0.0.0.dist-info/LICENSE
krml-0.0.0.dist-info/METADATA
krml-0.0.0.dist-info/WHEEL
krml-0.0.0.dist-info/entry_points.txt
krml-0.0.0.dist-info/RECORD
