Metadata-Version: 2.1
Name: krml
Version: 0.0.0
Summary: krml
Home-page: https://github.com/akyso168/krml
License: GPL-3.0
Author: Anthony So
Author-email: aso.job@gmail.com
Requires-Python: >=3.7,<4.0
Classifier: Development Status :: 1 - Planning
Classifier: License :: OSI Approved :: GNU General Public License v3 (GPLv3)
Classifier: Programming Language :: Python :: 3
Classifier: Programming Language :: Python :: 3.7
Classifier: Programming Language :: Python :: 3.8
Classifier: Programming Language :: Python :: 3.9
Classifier: Programming Language :: Python :: 3.10
Classifier: Programming Language :: Python :: 3.11
Requires-Dist: click (>=8.0.1)
Project-URL: Changelog, https://github.com/akyso168/krml/releases
Project-URL: Documentation, https://krml.readthedocs.io
Project-URL: Repository, https://github.com/akyso168/krml
